README.txt
setup.py
Products/__init__.py
Products.SharkbyteSSOPlugin.egg-info/PKG-INFO
Products.SharkbyteSSOPlugin.egg-info/SOURCES.txt
Products.SharkbyteSSOPlugin.egg-info/dependency_links.txt
Products.SharkbyteSSOPlugin.egg-info/entry_points.txt
Products.SharkbyteSSOPlugin.egg-info/namespace_packages.txt
Products.SharkbyteSSOPlugin.egg-info/not-zip-safe
Products.SharkbyteSSOPlugin.egg-info/requires.txt
Products.SharkbyteSSOPlugin.egg-info/top_level.txt
Products/SharkbyteSSOPlugin/SharkbyteSSOPlugin.py
Products/SharkbyteSSOPlugin/__init__.py
Products/SharkbyteSSOPlugin/version.txt
Products/SharkbyteSSOPlugin/zmi/sso.png
docs/HISTORY.txt
docs/LICENSE.txt