Metadata-Version: 1.0
Name: Products.SharkbyteSSOPlugin
Version: 0.6.0b1
Summary: SSO Plugin for Zope 2 PAS and PlonePAS
Home-page: http://plone.org/products/single-sign-on-plugin
Author: Ben Mason
Author-email: ben@sharkbyte.co.uk
License: GPL
Keywords: PAS SSO plugin
Platform: UNKNOWN
Classifier: Programming Language :: Python
Classifier: Framework :: Zope2
Classifier: Topic :: Security
